[
    {
        "run_id": "936dbc3f-7f6f-4233-a641-c8631738522e",
        "document_type": "Passport",
        "timestamp": "2025-04-19T06:42:50.476436",
        "fields": {
            "Selfie": "Face detected",
            "Passport Number": "12084097",
            "Surname": "THAKULLA KSHETRI",
            "Given Name": "PRITAN",
            "Nationality": "NPL",
            "Date of Birth": "12/08/2003",
            "Sex": "UNKNOWN",
            "Date of Expiration": "28/01/2031",
            "MRZ": "PSMPLTHAKULLA<KSHETRI<<PRITAN<<<<<<<<<<<<<<<\n12084097<5NPL0308120H310128569017603320<<<94"
        },
        "confidences": {
            "Selfie": 0.8042889833450317,
            "Passport Number": 0.9,
            "Surname": 0.9,
            "Given Name": 0.9,
            "Nationality": 0.9,
            "Date of Birth": 0.9,
            "Sex": 0.9,
            "Date of Expiration": 0.9,
            "MRZ": 0.9
        }
    }
]