[
    {
        "run_id": "citizenship",
        "document_type": "Citizenship",
        "timestamp": "2025-04-19T13:39:23.377757",
        "fields": {
            "Gender": "g E",
            "Name": "",
            "Father's Name": "",
            "Mother's Name": "",
            "Date of Birth": "",
            "Place of Birth": "",
            "Permanent Address": "",
            "Temporary Address": "",
            "Citizenship Number": "",
            "Issued District": "",
            "Spouse Name": "",
            "Grandfather's Name": "",
            "Issued Date": ""
        },
        "confidences": {
            "Gender": 0.578,
            "Name": 0.0,
            "Father's Name": 0.0,
            "Mother's Name": 0.0,
            "Date of Birth": 0.0,
            "Place of Birth": 0.0,
            "Permanent Address": 0.0,
            "Temporary Address": 0.0,
            "Citizenship Number": 0.0,
            "Issued District": 0.0,
            "Spouse Name": 0.0,
            "Grandfather's Name": 0.0,
            "Issued Date": 0.0
        }
    },
    {
        "run_id": "70b7b5b4-c344-4eb8-8e45-a86f1979bab3",
        "document_type": "Citizenship",
        "timestamp": "2025-04-19T13:39:23.531659",
        "fields": {
            "Gender": "g E"
        },
        "confidences": {
            "Gender": 0.578
        }
    }
]